flake8_drf/__init__.py
flake8_drf/constants.py
flake8_drf/plugin.py
flake8_drf-0.1.0.dist-info/entry_points.txt
flake8_drf-0.1.0.dist-info/WHEEL
flake8_drf-0.1.0.dist-info/METADATA
flake8_drf-0.1.0.dist-info/RECORD
